vaso/__init__.py
vaso-0.1.0.dist-info/METADATA
vaso-0.1.0.dist-info/WHEEL
vaso-0.1.0.dist-info/RECORD
